ipylar/__init__.py
ipylar/basins.py
ipylar/version.py
ipylar/data/RQ_era5_readme.txt
ipylar/data/amazonas_RQ_era5.csv
ipylar/data/amazonas_R_hybam.xlsx
ipylar/data/amazonas_divQ_era5.csv
ipylar/data/amazonas_grace_gsfc.csv
ipylar/data/amazonas_grace_utexas.csv
ipylar/data/congo_RQ_era5.csv
ipylar/data/congo_divQ_era5.csv
ipylar/data/congo_grace_gsfc.csv
ipylar/data/congo_grace_utexas.csv
ipylar/data/magdalena_output.csv
ipylar/data/mississippi_RQ_era5.csv
ipylar/data/mississippi_divQ_era5.csv
ipylar/data/mississippi_grace_gsfc.csv
ipylar/data/mississippi_grace_utexas.csv
ipylar/data/ob_RQ_era5.csv
ipylar/data/ob_divQ_era5.csv
ipylar/data/ob_grace_gsfc.csv
ipylar/data/ob_grace_utexas.csv
ipylar/data/parana_RQ_era5.csv
ipylar/data/parana_divQ_era5.csv
ipylar/data/parana_grace_gsfc.csv
ipylar/data/parana_grace_utexas.csv
ipylar/data/yenisei_RQ_era5.csv
ipylar/data/yenisei_divQ_era5.csv
ipylar/data/yenisei_grace_gsfc.csv
ipylar/data/yenisei_grace_utexas.csv
ipylar-1.0.7.dist-info/LICENSE
ipylar-1.0.7.dist-info/METADATA
ipylar-1.0.7.dist-info/WHEEL
ipylar-1.0.7.dist-info/entry_points.txt
ipylar-1.0.7.dist-info/top_level.txt
ipylar-1.0.7.dist-info/RECORD
