Metadata-Version: 2.1
Name: ipylar
Version: 1.0.7
Summary: Python utilities for the LAR model (Land Atmospheric Reservoir)
Home-page: https://pypi.org/project/ipylar
Author: Jorge I. Zuluaga, Ruben D. Molina, Juan F. Salazar and Jesus D. Gomez-Velez
Author-email: jorge.zuluaga@udea.edu.co
License: MIT
Keywords: hydrology,climate change
Classifier: Programming Language :: Python :: 3
Classifier: License :: OSI Approved :: MIT License
Classifier: Operating System :: OS Independent
License-File: LICENSE
Requires-Dist: matplotlib
Requires-Dist: pandas
